pipelinescope/__init__.py
pipelinescope/cli/__init__.py
pipelinescope/cli/diff.py
pipelinescope/core/__init__.py
pipelinescope/core/config.py
pipelinescope/core/entrypoint.py
pipelinescope/core/extrapolation.py
pipelinescope/core/profiler.py
pipelinescope/core/resource_monitor.py
pipelinescope/core/stats.py
pipelinescope/data/__init__.py
pipelinescope/data/serializer.py
pipelinescope/prompts/__init__.py
pipelinescope/prompts/llm_optimize.py
pipelinescope/reporting/__init__.py
pipelinescope/reporting/analyzer.py
pipelinescope/reporting/generator.py
pipelinescope/reporting/templates/summary.html
pipelinescope/utils/__init__.py
pipelinescope/utils/logger.py
pipelinescope-0.1.0.dist-info/licenses/LICENSE
pipelinescope-0.1.0.dist-info/METADATA
pipelinescope-0.1.0.dist-info/WHEEL
pipelinescope-0.1.0.dist-info/entry_points.txt
pipelinescope-0.1.0.dist-info/top_level.txt
pipelinescope-0.1.0.dist-info/RECORD
