Metadata-Version: 2.4
Name: pipelinescope
Version: 0.1.0
Summary: Simple, production-ready Python profiling for data pipelines
Author-email: SherozShaikh <shaikh.sheroz07@gmail.com>
License: MIT
Project-URL: Homepage, https://github.com/sherozshaikh/pipelinescope
Project-URL: Documentation, https://github.com/sherozshaikh/pipelinescope#readme
Project-URL: Repository, https://github.com/sherozshaikh/pipelinescope
Project-URL: Issues, https://github.com/sherozshaikh/pipelinescope/issues
Keywords: profiling,performance,pipeline,optimization,bottleneck
Classifier: Development Status :: 4 - Beta
Classifier: Intended Audience :: Developers
Classifier: License :: OSI Approved :: MIT License
Classifier: Programming Language :: Python :: 3
Classifier: Programming Language :: Python :: 3.8
Classifier: Programming Language :: Python :: 3.9
Classifier: Programming Language :: Python :: 3.10
Classifier: Programming Language :: Python :: 3.11
Classifier: Programming Language :: Python :: 3.12
Classifier: Topic :: Software Development :: Libraries :: Python Modules
Classifier: Topic :: System :: Monitoring
Requires-Python: >=3.8
License-File: LICENSE
Requires-Dist: psutil>=5.8.0
Requires-Dist: GPUtil>=1.4.0
Requires-Dist: pyyaml>=6.0
Requires-Dist: jinja2>=3.0.0
Requires-Dist: py-logex-enhanced>=0.1.3
Provides-Extra: dev
Requires-Dist: pytest>=7.0.0; extra == "dev"
Requires-Dist: pytest-cov>=4.0.0; extra == "dev"
Requires-Dist: black>=22.0.0; extra == "dev"
Requires-Dist: ruff>=0.1.0; extra == "dev"
Dynamic: license-file
